bibxml2.py
bibxml2-1.5.3.dist-info/METADATA
bibxml2-1.5.3.dist-info/WHEEL
bibxml2-1.5.3.dist-info/entry_points.txt
bibxml2-1.5.3.dist-info/RECORD
