Metadata-Version: 2.4
Name: bibxml2
Version: 1.5.1
Summary: A simple converter of MARCXML/PICAXML to CSV/TSV/parquet
Author-email: Eetu Mäkelä <eetu.makela@helsinki.fi>
License-Expression: MIT
Project-URL: repository, https://github.com/hsci-r/bibxml2
Keywords: MARCXML,PICA XML,bibliographic data,data conversion
Requires-Python: >=3.10
Requires-Dist: lxml>=5
Requires-Dist: click>=8
Requires-Dist: tqdm>=4
Requires-Dist: hsciutil>=0.1.2
Requires-Dist: fsspec>=2025
Requires-Dist: pyarrow>=20
Requires-Dist: s3fs>=2025
Requires-Dist: zstandard>=0.23.0
